tdam_api/__init__.py
tdam_api/client.py
tdam_api/common.py
tdam_api/entities.py
tdam_api/urls.py
tdam_api-0.1.0.dist-info/AUTHORS.rst
tdam_api-0.1.0.dist-info/LICENSE
tdam_api-0.1.0.dist-info/METADATA
tdam_api-0.1.0.dist-info/WHEEL
tdam_api-0.1.0.dist-info/top_level.txt
tdam_api-0.1.0.dist-info/RECORD
