Metadata-Version: 2.1
Name: tdam-api
Version: 0.1.0
Summary: A Python client for the TDAmeritrade Trading API
Home-page: https://github.com/jbasu/tdam_api
Author: Jyoti Basu
Author-email: jyotibasu@engineeredtrades.com
License: MIT
Keywords: tdam_api tdameritrade api trading stocks options
Platform: UNKNOWN
Classifier: Development Status :: 2 - Pre-Alpha
Classifier: Intended Audience :: Developers
Classifier: License :: OSI Approved :: MIT License
Classifier: Natural Language :: English
Classifier: Programming Language :: Python :: 3
Classifier: Programming Language :: Python :: 3.6
Requires-Dist: requests (>=2.22.0)
Requires-Dist: attrs (>=19.1.0)
Provides-Extra: pandas
Requires-Dist: pandas (>=0.25.0) ; extra == 'pandas'
